src/__init__.py
src/api.py
src/detectors.py
src/distance.py
src/embeddings.py
src/entities.py
src/face_embeddings.py
src/fusion.py
src/interfaces.py
src/model_manager.py
src/registry.py
src/utils.py
src/backbones/__init__.py
src/backbones/resnet50_circle_dg.py
deep_person-0.2.0.dist-info/METADATA
deep_person-0.2.0.dist-info/WHEEL
deep_person-0.2.0.dist-info/licenses/LICENSE
deep_person-0.2.0.dist-info/RECORD
