Metadata-Version: 2.4
Name: deep-person
Version: 0.2.0
Summary: Person re-identification component for Vbot framework
Project-URL: Homepage, https://github.com/VitaDynamics/DeepPerson
Project-URL: Repository, https://github.com/VitaDynamics/DeepPerson
Project-URL: Issues, https://github.com/VitaDynamics/DeepPerson/issues
Project-URL: Documentation, https://github.com/VitaDynamics/DeepPerson#readme
Author-email: VitaDynamics <info@vitadynamics.org>
License: MIT
License-File: LICENSE
Keywords: computer-vision,deep-learning,person-reid,resnet,yolo
Classifier: Development Status :: 4 - Beta
Classifier: Intended Audience :: Developers
Classifier: License :: OSI Approved :: MIT License
Classifier: Programming Language :: Python :: 3
Classifier: Programming Language :: Python :: 3.11
Classifier: Programming Language :: Python :: 3.12
Classifier: Programming Language :: Python :: 3.13
Classifier: Topic :: Scientific/Engineering :: Artificial Intelligence
Classifier: Topic :: Software Development :: Libraries :: Python Modules
Requires-Python: >=3.11
Requires-Dist: deepface>=0.0.95
Requires-Dist: gdown>=5.0.0
Requires-Dist: numpy>=1.24.0
Requires-Dist: pillow>=9.0.0
Requires-Dist: scikit-learn>=1.2.0
Requires-Dist: tf-keras>=2.18.0
Requires-Dist: torch>=2.0.0
Requires-Dist: torchvision>=0.15.0
Requires-Dist: tqdm>=4.64.0
Requires-Dist: ultralytics>=8.3.224
Provides-Extra: all
Requires-Dist: mypy>=1.0.0; extra == 'all'
Requires-Dist: pytest-cov>=4.0.0; extra == 'all'
Requires-Dist: pytest>=7.0.0; extra == 'all'
Requires-Dist: ruff>=0.8.0; extra == 'all'
Requires-Dist: ultralytics>=8.3.224; extra == 'all'
Provides-Extra: dev
Requires-Dist: mypy>=1.0.0; extra == 'dev'
Requires-Dist: pytest-cov>=4.0.0; extra == 'dev'
Requires-Dist: pytest>=7.0.0; extra == 'dev'
Requires-Dist: ruff>=0.8.0; extra == 'dev'
